LICENSE
MANIFEST.in
README.rst
setup.py
doc/conf.py
doc/index.rst
doc/make.bat
doc/.ropeproject/config.py
doc/src/todo.rst
doc/src/modules/analysis.bumps.rst
doc/src/modules/analysis.fields.rst
doc/src/modules/analysis.info.rst
doc/src/modules/analysis.registration.rst
doc/src/modules/analysis.signal.rst
doc/src/modules/analysis.spikes.rst
doc/src/modules/core.arena.rst
doc/src/modules/core.common.rst
doc/src/modules/index.rst
doc/src/modules/plotting.fields.rst
doc/src/overview/index.rst
doc/src/overview/.ropeproject/config.py
external/armadillo/include/armadillo
external/armadillo/include/armadillo_bits/BaseCube_bones.hpp
external/armadillo/include/armadillo_bits/BaseCube_meat.hpp
external/armadillo/include/armadillo_bits/Base_bones.hpp
external/armadillo/include/armadillo_bits/Base_meat.hpp
external/armadillo/include/armadillo_bits/Col_bones.hpp
external/armadillo/include/armadillo_bits/Col_meat.hpp
external/armadillo/include/armadillo_bits/Cube_bones.hpp
external/armadillo/include/armadillo_bits/Cube_meat.hpp
external/armadillo/include/armadillo_bits/GenCube_bones.hpp
external/armadillo/include/armadillo_bits/GenCube_meat.hpp
external/armadillo/include/armadillo_bits/Gen_bones.hpp
external/armadillo/include/armadillo_bits/Gen_meat.hpp
external/armadillo/include/armadillo_bits/GlueCube_bones.hpp
external/armadillo/include/armadillo_bits/GlueCube_meat.hpp
external/armadillo/include/armadillo_bits/Glue_bones.hpp
external/armadillo/include/armadillo_bits/Glue_meat.hpp
external/armadillo/include/armadillo_bits/Mat_bones.hpp
external/armadillo/include/armadillo_bits/Mat_meat.hpp
external/armadillo/include/armadillo_bits/OpCube_bones.hpp
external/armadillo/include/armadillo_bits/OpCube_meat.hpp
external/armadillo/include/armadillo_bits/Op_bones.hpp
external/armadillo/include/armadillo_bits/Op_meat.hpp
external/armadillo/include/armadillo_bits/Proxy.hpp
external/armadillo/include/armadillo_bits/ProxyCube.hpp
external/armadillo/include/armadillo_bits/Row_bones.hpp
gridcells.egg-info/PKG-INFO
gridcells.egg-info/SOURCES.txt
gridcells.egg-info/dependency_links.txt
gridcells.egg-info/requires.txt
gridcells.egg-info/top_level.txt
