Metadata-Version: 1.0
Name: gridcells
Version: 0.1.3
Summary: Package for grid cell analysis and simulation.
Home-page: https://github.com/lsolanka/gridcells
Author: Lukas Solanka
Author-email: lsolanka@gmail.com
License: GPL
Platform: UNKNOWN
